{
    "basic_info": {
      "description_header": "Hi",
      "description": "👋 I'm HOANG Minh Chau. FULLSTACK JAVASCRIPT WEB DEVELOPER. After experiences in the civil engineering industry, I am now moving into the IT development world. Link between my initial training and my future professional: my appetite for technology and the design of new products. I'm now developer at Campus At Work (https://campusatwork.fr). 💜",
      "section_name": {
        "about": "About me",
        "projects": "Projects",
        "skills": "Skills",
        "experience": "Experience"
      }
    },
    "projects": [
      {
        "title": "Search Band",
        "startDate": "2021",
        "description": "By using the MusicBrainz API, the website allow us to find the artist that we want and also displays that artist's releases.",
        "images": [
          "images/portfolio/searchBand/searchBand-1.PNG",
          "images/portfolio/searchBand/searchBand-2.PNG",
          "images/portfolio/searchBand/searchBand-3.PNG"
        ],
        "url": "https://search-band-lacapsule.glitch.me",
        "github": "https://github.com/ninjacanthi1995/searchBand",
        "technologies": [
          {
            "class": "devicon-html5-plain",
            "name": "HTML5"
          },
          {
            "class": "devicon-javascript-plain",
            "name": "Javascript"
          },
          {
            "class": "devicon-bootstrap-plain",
            "name": "Bootstrap"
          },
          {
            "class": "devicon-react-original",
            "name": "React"
          },
          {
            "class": "devicon-nodejs-plain",
            "name": "NodeJS"
          },
          {
            "class": "devicon-express-original",
            "name": "Express"
          },
          {
            "class": "devicon-amazonwebservices-original",
            "name": "AWS"
          },
          {
            "class": "devicon-git-plain",
            "name": "Git"
          },
          {
            "class": "devicon-github-original",
            "name": "GitHub"
          }
        ]
      },
      {
        "title": "My Back Office",
        "startDate": "2021",
        "description": "The Website allow us to set up a Back Office to manage your contact list.",
        "images": [
          "images/portfolio/monBackOffice/monBackOffice-1.PNG",
          "images/portfolio/monBackOffice/monBackOffice-2.PNG",
          "images/portfolio/monBackOffice/monBackOffice-3.PNG"
        ],
        "url": "https://my-backoffice-lacapsule.glitch.me",
        "github": "https://github.com/ninjacanthi1995/monBackOffice",
        "technologies": [
          {
            "class": "devicon-html5-plain",
            "name": "HTML5"
          },
          {
            "class": "devicon-javascript-plain",
            "name": "Javascript"
          },
          {
            "class": "devicon-bootstrap-plain",
            "name": "Bootstrap"
          },
          {
            "class": "devicon-react-original",
            "name": "React"
          },
          {
            "class": "devicon-nodejs-plain",
            "name": "NodeJS"
          },
          {
            "class": "devicon-express-original",
            "name": "Express"
          },
          {
            "class": "devicon-mongodb-plain",
            "name": "MongoDB"
          },
          {
            "class": "devicon-amazonwebservices-original",
            "name": "AWS"
          },
          {
            "class": "devicon-git-plain",
            "name": "Git"
          },
          {
            "class": "devicon-github-original",
            "name": "GitHub"
          }
        ]
      },
      {
        "title": "Populate Library",
        "startDate": "2021",
        "description": "The website offer us, via several forms, the possibility to add readers, add books and add a book to a reader's favorite.",
        "images": [
          "images/portfolio/populateLibrary/populateLibrary-1.PNG",
          "images/portfolio/populateLibrary/populateLibrary-2.PNG",
          "images/portfolio/populateLibrary/populateLibrary-3.PNG"
        ],
        "url": "https://populate-library-lacapsule.glitch.me",
        "github": "https://github.com/ninjacanthi1995/populate-library",
        "technologies": [
          {
            "class": "devicon-html5-plain",
            "name": "HTML5"
          },
          {
            "class": "devicon-javascript-plain",
            "name": "Javascript"
          },
          {
            "class": "devicon-bootstrap-plain",
            "name": "Bootstrap"
          },
          {
            "class": "devicon-react-original",
            "name": "React"
          },
          {
            "class": "devicon-nodejs-plain",
            "name": "NodeJS"
          },
          {
            "class": "devicon-express-original",
            "name": "Express"
          },
          {
            "class": "devicon-mongodb-plain",
            "name": "MongoDB"
          },
          {
            "class": "devicon-amazonwebservices-original",
            "name": "AWS"
          },
          {
            "class": "devicon-git-plain",
            "name": "Git"
          },
          {
            "class": "devicon-github-original",
            "name": "GitHub"
          }
        ]
      },
      {
        "title": "Nested Blog",
        "startDate": "2021",
        "description": "The website works like a mini blog with comments management.",
        "images": [
          "images/portfolio/nestedBlog/nestedBlog-1.PNG",
          "images/portfolio/nestedBlog/nestedBlog-2.PNG"
        ],
        "url": "https://nested-blog-lacapsule.glitch.me",
        "github": "https://github.com/ninjacanthi1995/nested-blog",
        "technologies": [
          {
            "class": "devicon-html5-plain",
            "name": "HTML5"
          },
          {
            "class": "devicon-javascript-plain",
            "name": "Javascript"
          },
          {
            "class": "devicon-bootstrap-plain",
            "name": "Bootstrap"
          },
          {
            "class": "devicon-react-original",
            "name": "React"
          },
          {
            "class": "devicon-nodejs-plain",
            "name": "NodeJS"
          },
          {
            "class": "devicon-express-original",
            "name": "Express"
          },
          {
            "class": "devicon-mongodb-plain",
            "name": "MongoDB"
          },
          {
            "class": "devicon-amazonwebservices-original",
            "name": "AWS"
          },
          {
            "class": "devicon-git-plain",
            "name": "Git"
          },
          {
            "class": "devicon-github-original",
            "name": "GitHub"
          }
        ]
      },
      {
        "title": "Weather App",
        "startDate": "2021",
        "description": "The web application allows you to display a city's weather forecast on an interactive map.",
        "images": [
          "images/portfolio/weatherApp/weatherApp-1.PNG",
          "images/portfolio/weatherApp/weatherApp-2.PNG",
          "images/portfolio/weatherApp/weatherApp-3.PNG"
        ],
        "url": "https://weather-app-lacapsule.glitch.me",
        "github": "https://github.com/ninjacanthi1995/weather-app",
        "technologies": [
          {
            "class": "",
            "name": "API Leaflet"
          },
          {
            "class": "devicon-html5-plain",
            "name": "HTML5"
          },
          {
            "class": "devicon-javascript-plain",
            "name": "Javascript"
          },
          {
            "class": "devicon-bootstrap-plain",
            "name": "Bootstrap"
          },
          {
            "class": "devicon-react-original",
            "name": "React"
          },
          {
            "class": "devicon-nodejs-plain",
            "name": "NodeJS"
          },
          {
            "class": "devicon-express-original",
            "name": "Express"
          },
          {
            "class": "devicon-mongodb-plain",
            "name": "MongoDB"
          },
          {
            "class": "devicon-amazonwebservices-original",
            "name": "AWS"
          },
          {
            "class": "devicon-git-plain",
            "name": "Git"
          },
          {
            "class": "devicon-github-original",
            "name": "GitHub"
          }
        ]
      },
      {
        "title": "Ticetac",
        "startDate": "2021",
        "description": "The train ticket reservation site.",
        "images": [
          "images/portfolio/ticetac/ticetac-1.PNG",
          "images/portfolio/ticetac/ticetac-2.PNG",
          "images/portfolio/ticetac/ticetac-3.PNG",
          "images/portfolio/ticetac/ticetac-4.PNG",
          "images/portfolio/ticetac/ticetac-5.PNG",
          "images/portfolio/ticetac/ticetac-6.PNG"
        ],
        "url": "https://ticetac.herokuapp.com/",
        "github": "https://github.com/ninjacanthi1995/ticetac",
        "technologies": [
          {
            "class": "devicon-html5-plain",
            "name": "HTML5"
          },
          {
            "class": "devicon-javascript-plain",
            "name": "Javascript"
          },
          {
            "class": "devicon-bootstrap-plain",
            "name": "Bootstrap"
          },
          {
            "class": "devicon-react-original",
            "name": "React"
          },
          {
            "class": "devicon-nodejs-plain",
            "name": "NodeJS"
          },
          {
            "class": "devicon-express-original",
            "name": "Express"
          },
          {
            "class": "devicon-mongodb-plain",
            "name": "MongoDB"
          },
          {
            "class": "devicon-heroku-original",
            "name": "Heroku"
          },
          {
            "class": "devicon-git-plain",
            "name": "Git"
          },
          {
            "class": "devicon-github-original",
            "name": "GitHub"
          }
        ]
      },
      {
        "title": "Street Fighter",
        "startDate": "2021",
        "description": "The menu for selecting your players on Street Fighter.",
        "images": [
          "images/portfolio/street-fighter/street-fighter-1.PNG",
          "images/portfolio/street-fighter/street-fighter-2.PNG"
        ],
        "url": "https://ninjacanthi1995.github.io/street-fighter/",
        "github": "https://github.com/ninjacanthi1995/street-fighter",
        "technologies": [
          {
            "class": "devicon-html5-plain",
            "name": "HTML5"
          },
          {
            "class": "devicon-javascript-plain",
            "name": "Javascript"
          },
          {
            "class": "devicon-bootstrap-plain",
            "name": "Bootstrap"
          },
          {
            "class": "devicon-react-original",
            "name": "React"
          },
          {
            "class": "devicon-react-original",
            "name": "ReactJS"
          },
          {
            "class": "devicon-nodejs-plain",
            "name": "NodeJS"
          },
          {
            "class": "devicon-git-plain",
            "name": "Git"
          },
          {
            "class": "devicon-github-original",
            "name": "GitHub"
          }
        ]
      },
      {
        "title": "Space Tourism",
        "startDate": "2021",
        "description": "Frontendmentor multipage space tourism website challenge",
        "images": [
          "images/portfolio/space-tourism/img-1.PNG",
          "images/portfolio/space-tourism/img-2.PNG",
          "images/portfolio/space-tourism/img-3.PNG",
          "images/portfolio/space-tourism/img-4.PNG"
        ],
        "url": "https://space-tourism-chou.netlify.app",
        "github": "https://github.com/ninjacanthi1995/space-tourism",
        "technologies": [
          {
            "class": "devicon-html5-plain",
            "name": "HTML5"
          },
          {
            "class": "devicon-sass-original",
            "name": "Sass"
          },
          {
            "class": "devicon-javascript-plain",
            "name": "Javascript"
          },
          {
            "class": "devicon-react-original",
            "name": "React"
          },
          {
            "class": "devicon-git-plain",
            "name": "Git"
          },
          {
            "class": "devicon-github-original",
            "name": "GitHub"
          }
        ]
      },
      {
        "title": "E-commerce Product Page",
        "startDate": "2021",
        "description": "Frontendmentor e-commerce product page challenge",
        "images": [
          "images/portfolio/e-commerce-product-page/img-1.jpg",
          "images/portfolio/e-commerce-product-page/img-2.jpg",
          "images/portfolio/e-commerce-product-page/img-3.jpg",
          "images/portfolio/e-commerce-product-page/img-4.jpg",
          "images/portfolio/e-commerce-product-page/img-5.jpg",
          "images/portfolio/e-commerce-product-page/img-6.jpg",
          "images/portfolio/e-commerce-product-page/img-7.jpg",
          "images/portfolio/e-commerce-product-page/img-8.jpg",
          "images/portfolio/e-commerce-product-page/img-9.jpg",
          "images/portfolio/e-commerce-product-page/img-10.jpg"
        ],
        "url": "https://ecommerce-product-landing-page-chou.netlify.app/",
        "github": "https://github.com/ninjacanthi1995/ecommerce-product-page",
        "technologies": [
          {
            "class": "devicon-html5-plain",
            "name": "HTML5"
          },
          {
            "class": "devicon-sass-original",
            "name": "Sass"
          },
          {
            "class": "devicon-javascript-plain",
            "name": "Javascript"
          },
          {
            "class": "devicon-react-original",
            "name": "React"
          },
          {
            "class": "devicon-git-plain",
            "name": "Git"
          },
          {
            "class": "devicon-github-original",
            "name": "GitHub"
          }
        ]
      },
      {
        "title": "Rock, Paper, Scissors game",
        "startDate": "2021",
        "description": "Frontendmentor Rock, Paper, Scissors game challenge",
        "images": [
          "images/portfolio/rock-paper-scissors/img-1.jpg",
          "images/portfolio/rock-paper-scissors/img-2.jpg",
          "images/portfolio/rock-paper-scissors/img-3.jpg",
          "images/portfolio/rock-paper-scissors/img-4.jpg",
          "images/portfolio/rock-paper-scissors/img-5.jpg",
          "images/portfolio/rock-paper-scissors/img-6.jpg",
          "images/portfolio/rock-paper-scissors/img-7.jpg",
          "images/portfolio/rock-paper-scissors/img-8.jpg",
          "images/portfolio/rock-paper-scissors/img-9.jpg",
          "images/portfolio/rock-paper-scissors/img-10.jpg"
        ],
        "url": "https://rock-paper-scissors-spock-lizard-chou.netlify.app/",
        "github": "https://github.com/ninjacanthi1995/Rock-paper-scissors",
        "technologies": [
          {
            "class": "devicon-html5-plain",
            "name": "HTML5"
          },
          {
            "class": "devicon-sass-original",
            "name": "Sass"
          },
          {
            "class": "devicon-javascript-plain",
            "name": "Javascript"
          },
          {
            "class": "devicon-react-original",
            "name": "React"
          },
          {
            "class": "devicon-git-plain",
            "name": "Git"
          },
          {
            "class": "devicon-github-original",
            "name": "GitHub"
          }
        ]
      },
      {
        "title": "REST Countries API",
        "startDate": "2021",
        "description": "Frontendmentor REST Countries API with color theme switcher challenge",
        "images": [
          "images/portfolio/rest-countries-api/img-1.jpg",
          "images/portfolio/rest-countries-api/img-2.jpg",
          "images/portfolio/rest-countries-api/img-3.jpg",
          "images/portfolio/rest-countries-api/img-4.jpg",
          "images/portfolio/rest-countries-api/img-5.jpg",
          "images/portfolio/rest-countries-api/img-6.jpg",
          "images/portfolio/rest-countries-api/img-7.jpg",
          "images/portfolio/rest-countries-api/img-8.jpg",
          "images/portfolio/rest-countries-api/img-9.jpg"
        ],
        "url": "https://rest-country-api-chou.netlify.app",
        "github": "https://github.com/ninjacanthi1995/rest-countries-api",
        "technologies": [
          {
            "class": "devicon-html5-plain",
            "name": "HTML5"
          },
          {
            "class": "devicon-sass-original",
            "name": "Sass"
          },
          {
            "class": "devicon-javascript-plain",
            "name": "Javascript"
          },
          {
            "class": "devicon-react-original",
            "name": "React"
          },
          {
            "class": "devicon-git-plain",
            "name": "Git"
          },
          {
            "class": "devicon-github-original",
            "name": "GitHub"
          }
        ]
      },
      {
        "title": "NFT preview card",
        "startDate": "2021",
        "description": "Frontendmentor NFT preview card component challenge",
        "images": [
          "images/portfolio/nft-preview-card-component/img-1.jpg",
          "images/portfolio/nft-preview-card-component/img-2.jpg",
          "images/portfolio/nft-preview-card-component/img-3.jpg"
        ],
        "url": "https://nft-preview-card-chou.netlify.app/",
        "github": "https://github.com/ninjacanthi1995/nft-preview-card-component",
        "technologies": [
          {
            "class": "devicon-dart-plain",
            "name": "Dart"
          },
          {
            "class": "devicon-flutter-plain",
            "name": "Flutter"
          },
          {
            "class": "devicon-git-plain",
            "name": "Git"
          },
          {
            "class": "devicon-github-original",
            "name": "GitHub"
          }
        ]
      },
      {
        "title": "Pricing component with toggle",
        "startDate": "2021",
        "description": "Frontendmentor Pricing component with toggle challenge",
        "images": [
          "images/portfolio/pricing-component-with-toggle/img-1.jpg",
          "images/portfolio/pricing-component-with-toggle/img-2.jpg",
          "images/portfolio/pricing-component-with-toggle/img-3.jpg",
          "images/portfolio/pricing-component-with-toggle/img-3.jpg"
        ],
        "url": "https://pricing-component-with-toggle-chou.netlify.app",
        "github": "https://github.com/ninjacanthi1995/pricing-component-with-toggle",
        "technologies": [
          {
            "class": "devicon-dart-plain",
            "name": "Dart"
          },
          {
            "class": "devicon-flutter-plain",
            "name": "Flutter"
          },
          {
            "class": "devicon-git-plain",
            "name": "Git"
          },
          {
            "class": "devicon-github-original",
            "name": "GitHub"
          }
        ]
      },
      {
        "title": "Campus At Work admin platform",
        "startDate": "2021",
        "description": "Admin page allowing non-IT staffs to modify the main page campusatwork.fr and to manage its visitors.",
        "images": [
          "images/portfolio/caw-admin/img-1.png",
          "images/portfolio/caw-admin/img-2.png",
          "images/portfolio/caw-admin/img-3.png",
          "images/portfolio/caw-admin/img-4.png",
          "images/portfolio/caw-admin/img-5.png"
        ],
        "url": "https://admin.campusatwork.fr",
        "github": "",
        "technologies": [
          {
            "class": "devicon-html5-plain",
            "name": "HTML5"
          },
          {
            "class": "devicon-sass-original",
            "name": "Sass"
          },
          {
            "class": "devicon-javascript-plain",
            "name": "Javascript"
          },
          {
            "class": "devicon-typescript-plain",
            "name": "Typescript"
          },
          {
            "class": "devicon-angularjs-plain",
            "name": "Angular"
          },
          {
            "class": "devicon-nodejs-plain",
            "name": "NodeJS"
          },
          {
            "class": "devicon-mongodb-plain",
            "name": "MongoDB"
          },
          {
            "class": "devicon-git-plain",
            "name": "Git"
          },
          {
            "class": "devicon-github-original",
            "name": "GitHub"
          }
        ]
      },
      {
        "title": "Campus At Work LMS admin platform",
        "startDate": "2021",
        "description": "Admin page allowing non-IT staffs to modify the LMS (learning management system) page learning.campusatwork.fr and its users.",
        "images": [
          "images/portfolio/caw-lms-admin/img-1.png",
          "images/portfolio/caw-lms-admin/img-2.png",
          "images/portfolio/caw-lms-admin/img-3.png",
          "images/portfolio/caw-lms-admin/img-4.png"
        ],
        "url": "https://learning.campusatwork.fr/",
        "github": "",
        "technologies": [
          {
            "class": "devicon-html5-plain",
            "name": "HTML5"
          },
          {
            "class": "devicon-sass-original",
            "name": "Sass"
          },
          {
            "class": "devicon-javascript-plain",
            "name": "Javascript"
          },
          {
            "class": "devicon-typescript-plain",
            "name": "Typescript"
          },
          {
            "class": "devicon-angularjs-plain",
            "name": "Angular"
          },
          {
            "class": "devicon-nodejs-plain",
            "name": "NodeJS"
          },
          {
            "class": "devicon-mongodb-plain",
            "name": "MongoDB"
          },
          {
            "class": "devicon-git-plain",
            "name": "Git"
          },
          {
            "class": "devicon-github-original",
            "name": "GitHub"
          }
        ]
      },
      {
        "title": "Campus Academy website",
        "startDate": "2022",
        "description": "Restructuring of the Campus Academy website. Project done within a week in collaboration with 3 others devs.",
        "images": [
          "images/portfolio/campus-academy/img-1.png",
          "images/portfolio/campus-academy/img-2.png",
          "images/portfolio/campus-academy/img-3.png",
          "images/portfolio/campus-academy/img-4.png"
        ],
        "url": "https://campusacademy.fr",
        "github": "",
        "technologies": [
          {
            "class": "devicon-html5-plain",
            "name": "HTML5"
          },
          {
            "class": "devicon-sass-original",
            "name": "Sass"
          },
          {
            "class": "devicon-javascript-plain",
            "name": "Javascript"
          },
          {
            "class": "devicon-angularjs-plain",
            "name": "Angular"
          },
          {
            "class": "devicon-nodejs-plain",
            "name": "NodeJS"
          },
          {
            "class": "devicon-mongodb-plain",
            "name": "MongoDB"
          },
          {
            "class": "devicon-git-plain",
            "name": "Git"
          },
          {
            "class": "devicon-github-original",
            "name": "GitHub"
          }
        ]
      }
    ],
    "experience": [
      {
        "company": "Campus At Work",
        "title": "Full-stack Javascript Web Developer",
        "years": "08.2021 - Now",
        "mainTech": [
          "Angular NodeJS MongoDB"
        ],
        "technologies": [
          "HTML",
          "CSS",
          "JavaScript",
          "Angular",
          "NodeJS",
          "Express",
          "MongoDB",
          "Git",
          "Github",
          "Responsive Design"
        ]
      },
      {
        "company": "La Capsule",
        "title": "Full-stack Javascript Web and Mobile Developement Student",
        "years": "05.2021 - 08-2021",
        "mainTech": [
          "ReactJS NodeJS MongoDB"
        ],
        "technologies": [
          "HTML",
          "CSS",
          "JavaScript",
          "jQuery",
          "Bootstrap",
          "React",
          "Redux",
          "NodeJS",
          "Express",
          "MongoDB",
          "Git",
          "Github",
          "Responsive Design"
        ]
      },
      {
        "company": "Tractebel Engineering France",
        "title": "Structural Engineer",
        "years": "08.2019 - 05.2021",
        "mainTech": [
          "Engineering Skills"
        ],
        "technologies": [
          "Modeling",
          "Technical Documents Writing",
          "Programming",
          "Structural Analysis"
        ]
      },
      {
        "company": "INSA Lyon",
        "title": "Civil Engineering Student",
        "years": "2014 - 2019",
        "mainTech": [
          "Civil Engineering"
        ],
        "technologies": [
          "Civil Engineering Skills"
        ]
      },
      {
        "company": "Phan Boi Chau Specialized School",
        "title": "IT Specialized Class Student",
        "years": "2012 - 2013",
        "mainTech": [
          "High School"
        ],
        "technologies": [
          "3rd Prize", "in National Olympiad in Informatics", "for High School Students"
        ]
      }
    ]
  }